lambda_invoke/__init__.py
lambda_invoke/simple_proxy.py
lambda_invoke-0.6.dist-info/AUTHORS.rst
lambda_invoke-0.6.dist-info/LICENSE
lambda_invoke-0.6.dist-info/METADATA
lambda_invoke-0.6.dist-info/WHEEL
lambda_invoke-0.6.dist-info/top_level.txt
lambda_invoke-0.6.dist-info/RECORD
